[
    {
        "id": "P000293",
        "source": [
            "Salt Lake",
            "Ultadanga",
            "Esplanade"
        ],
        "destination": "Howrah Station",
        "count": 9,
        "timestamp": "16:51:23"
    },
    {
        "id": "P000572",
        "source": [
            "Garia",
            "Jadavpur",
            "Ballygunge"
        ],
        "destination": "Sealdah",
        "count": 9,
        "timestamp": "16:53:09"
    },
    {
        "id": "P001683",
        "source": [
            "Ultadanga",
            "Salt Lake",
            "New Town"
        ],
        "destination": "Chinar Park",
        "count": 8,
        "timestamp": "16:53:23"
    },
    {
        "id": "P001705",
        "source": [
            "Gariahat",
            "Ballygunge",
            "Park Circus"
        ],
        "destination": "Sealdah",
        "count": 10,
        "timestamp": "16:50:26"
    },
    {
        "id": "P002347",
        "source": [
            "Bagbazar",
            "Shyambazar",
            "Esplanade"
        ],
        "destination": "Ruby Hospital",
        "count": 2,
        "timestamp": "16:54:25"
    },
    {
        "id": "P002530",
        "source": [
            "Ballygunge",
            "Sealdah",
            "MG Road"
        ],
        "destination": "Howrah Station",
        "count": 2,
        "timestamp": "16:51:50"
    },
    {
        "id": "P002790",
        "source": [
            "Howrah Station",
            "Esplanade",
            "Kalighat"
        ],
        "destination": "Garia",
        "count": 8,
        "timestamp": "16:53:11"
    }
]