[
    {
        "id": "P000127",
        "source": [
            "Sealdah",
            "Moulali",
            "Park Circus"
        ],
        "destination": "Rashbehari",
        "count": 10,
        "timestamp": "4:52:49"
    },
    {
        "id": "P000151",
        "source": [
            "Ripon Street",
            "SN Banerjee",
            "Lalbazar"
        ],
        "destination": "Howrah Station",
        "count": 5,
        "timestamp": "4:51:06"
    },
    {
        "id": "P000296",
        "source": [
            "Phoolbagan",
            "Park Circus",
            "Ruby"
        ],
        "destination": "Garia",
        "count": 8,
        "timestamp": "4:51:42"
    },
    {
        "id": "P000335",
        "source": [
            "Gariahat",
            "Golpark",
            "Hazra"
        ],
        "destination": "Esplanade",
        "count": 9,
        "timestamp": "4:50:07"
    },
    {
        "id": "P000403",
        "source": [
            "Garia",
            "Kamalgazi",
            "Narendrapur"
        ],
        "destination": "Sonarpur",
        "count": 10,
        "timestamp": "4:50:19"
    },
    {
        "id": "P000420",
        "source": [
            "Dhakuria",
            "Gariahat",
            "Rashbehari"
        ],
        "destination": "Esplanade",
        "count": 7,
        "timestamp": "4:53:14"
    },
    {
        "id": "P000594",
        "source": [
            "Jadavpur",
            "Kasba",
            "Bosepukur"
        ],
        "destination": "Gariahat",
        "count": 7,
        "timestamp": "4:53:27"
    },
    {
        "id": "P000847",
        "source": [
            "Jadavpur",
            "Kasba",
            "Bosepukur"
        ],
        "destination": "Gariahat",
        "count": 3,
        "timestamp": "4:54:00"
    },
    {
        "id": "P000958",
        "source": [
            "Ruby",
            "Gariahat",
            "Ultadanga"
        ],
        "destination": "Airport Gate No. 1",
        "count": 10,
        "timestamp": "4:54:15"
    },
    {
        "id": "P001221",
        "source": [
            "Garia",
            "Ruby",
            "Ultadanga"
        ],
        "destination": "Salt Lake",
        "count": 3,
        "timestamp": "4:52:13"
    },
    {
        "id": "P001349",
        "source": [
            "Dumdum",
            "Belgachia",
            "Shyambazar"
        ],
        "destination": "Tollygunge",
        "count": 7,
        "timestamp": "4:53:53"
    },
    {
        "id": "P001811",
        "source": [
            "Esplanade",
            "Ultadanga",
            "Salt Lake"
        ],
        "destination": "Rajarhat",
        "count": 5,
        "timestamp": "4:54:55"
    },
    {
        "id": "P002295",
        "source": [
            "Howrah Station",
            "Esplanade",
            "Kalighat"
        ],
        "destination": "Jadavpur",
        "count": 6,
        "timestamp": "4:51:17"
    }
]