[
    {
        "id": "P000200",
        "source": [
            "Garia",
            "Jadavpur",
            "Kalighat"
        ],
        "destination": "Howrah Station",
        "count": 4,
        "timestamp": "7:36:01"
    },
    {
        "id": "P000201",
        "source": [
            "Shyambazar",
            "Beleghata",
            "Phoolbagan"
        ],
        "destination": "Sector V",
        "count": 2,
        "timestamp": "7:38:24"
    },
    {
        "id": "P000202",
        "source": [
            "Jadavpur",
            "Dhakuria",
            "Gariahat"
        ],
        "destination": "Bosepukur",
        "count": 1,
        "timestamp": "7:35:41"
    },
    {
        "id": "P000203",
        "source": [
            "College More",
            "New Town",
            "Unitech"
        ],
        "destination": "ECO Park",
        "count": 2,
        "timestamp": "7:38:04"
    },
    {
        "id": "P000204",
        "source": [
            "Howrah Station",
            "Esplanade",
            "Minto Park"
        ],
        "destination": "Patuli",
        "count": 2,
        "timestamp": "7:37:58"
    },
    {
        "id": "P000205",
        "source": [
            "Jadavpur",
            "Kasba",
            "Bosepukur"
        ],
        "destination": "Ruby",
        "count": 6,
        "timestamp": "7:37:36"
    },
    {
        "id": "P000206",
        "source": [
            "VIP Road",
            "Ultadanga",
            "Ruby"
        ],
        "destination": "Garia",
        "count": 1,
        "timestamp": "7:35:39"
    },
    {
        "id": "P000207",
        "source": [
            "Shyambazar",
            "Baranagar",
            "Dunlop"
        ],
        "destination": "Titagarh",
        "count": 6,
        "timestamp": "7:39:53"
    },
    {
        "id": "P000208",
        "source": [
            "Ultadanga",
            "Salt Lake",
            "New Town"
        ],
        "destination": "Airport",
        "count": 5,
        "timestamp": "7:36:21"
    }
]