[
    {
        "id": "P000832",
        "source": [
            "Esplanade",
            "Ultadanga",
            "Salt Lake"
        ],
        "destination": "New Town",
        "count": 2,
        "timestamp": "13:26:03"
    },
    {
        "id": "P000833",
        "source": [
            "Ultadanga",
            "VIP Road",
            "Airport Gate No. 1"
        ],
        "destination": "Barasat",
        "count": 4,
        "timestamp": "13:27:08"
    },
    {
        "id": "P000834",
        "source": [
            "Esplanade",
            "Minto Park",
            "Gariahat"
        ],
        "destination": "Patuli",
        "count": 1,
        "timestamp": "13:28:58"
    },
    {
        "id": "P000835",
        "source": [
            "Esplanade",
            "Ultadanga",
            "Karunamoyee"
        ],
        "destination": "New Town",
        "count": 6,
        "timestamp": "13:26:19"
    },
    {
        "id": "P000836",
        "source": [
            "Park Circus",
            "Ruby",
            "Garia"
        ],
        "destination": "Sonarpur",
        "count": 6,
        "timestamp": "13:28:10"
    },
    {
        "id": "P000837",
        "source": [
            "Park Circus",
            "MG Road",
            "Shyambazar"
        ],
        "destination": "Baranagar",
        "count": 6,
        "timestamp": "13:26:53"
    },
    {
        "id": "P000838",
        "source": [
            "Unitech",
            "Eco Space",
            "Aliah University"
        ],
        "destination": "City",
        "count": 3,
        "timestamp": "13:25:21"
    }
]