[
    {
        "id": "P000878",
        "source": [
            "Thakurpukur",
            "Behala",
            "Sakherbazar"
        ],
        "destination": "Alipore",
        "count": 4,
        "timestamp": "13:53:35"
    },
    {
        "id": "P000879",
        "source": [
            "Gariahat",
            "Phoolbagan",
            "Ultadanga"
        ],
        "destination": "Dumdum",
        "count": 4,
        "timestamp": "13:53:33"
    },
    {
        "id": "P000880",
        "source": [
            "Salt Lake Sector V",
            "Karunamoyee",
            "Ultadanga"
        ],
        "destination": "Phoolbagan",
        "count": 3,
        "timestamp": "13:54:57"
    },
    {
        "id": "P000881",
        "source": [
            "New Town",
            "Eco Park",
            "Chinar Park"
        ],
        "destination": "Airport",
        "count": 6,
        "timestamp": "13:50:15"
    },
    {
        "id": "P000882",
        "source": [
            "Newtown",
            "Salt Lake",
            "Ultadanga"
        ],
        "destination": "Howrah Station",
        "count": 5,
        "timestamp": "13:51:55"
    },
    {
        "id": "P000883",
        "source": [
            "Behala",
            "Sakherbazar",
            "New Alipore"
        ],
        "destination": "Minto Park",
        "count": 5,
        "timestamp": "13:51:51"
    },
    {
        "id": "P000884",
        "source": [
            "Gariahat",
            "Rashbehari",
            "Kalighat"
        ],
        "destination": "Esplanade",
        "count": 6,
        "timestamp": "13:54:58"
    },
    {
        "id": "P000885",
        "source": [
            "Jadavpur",
            "Kalighat",
            "Esplanade"
        ],
        "destination": "Howrah Station",
        "count": 5,
        "timestamp": "13:51:09"
    },
    {
        "id": "P000886",
        "source": [
            "Dumdum",
            "VIP Road",
            "Ultadanga"
        ],
        "destination": "Ruby",
        "count": 2,
        "timestamp": "13:50:12"
    },
    {
        "id": "P000887",
        "source": [
            "Dunlop",
            "BT Road",
            "Tobin Road"
        ],
        "destination": "Barrackpore",
        "count": 2,
        "timestamp": "13:51:45"
    }
]