[
    {
        "id": "P001054",
        "source": [
            "Jadavpur",
            "Kalighat",
            "Esplanade"
        ],
        "destination": "Howrah Station",
        "count": 1,
        "timestamp": "15:22:36"
    },
    {
        "id": "P001055",
        "source": [
            "Barasat",
            "Dumdum",
            "VIP Road"
        ],
        "destination": "Ruby",
        "count": 5,
        "timestamp": "15:23:29"
    },
    {
        "id": "P001056",
        "source": [
            "Park Street",
            "Sealdah",
            "Phoolbagan"
        ],
        "destination": "Dumdum",
        "count": 6,
        "timestamp": "15:23:29"
    },
    {
        "id": "P001057",
        "source": [
            "Garia",
            "Jadavpur",
            "Ballygunge"
        ],
        "destination": "Sealdah",
        "count": 3,
        "timestamp": "15:23:27"
    },
    {
        "id": "P001058",
        "source": [
            "Park Circus",
            "Ripon Street",
            "SN Banerjee"
        ],
        "destination": "Howrah Station",
        "count": 3,
        "timestamp": "15:21:14"
    },
    {
        "id": "P001059",
        "source": [
            "Gariahat",
            "Phoolbagan",
            "Ultadanga"
        ],
        "destination": "Dumdum",
        "count": 1,
        "timestamp": "15:23:13"
    },
    {
        "id": "P001060",
        "source": [
            "Park Street",
            "Sealdah",
            "Phoolbagan"
        ],
        "destination": "Dumdum",
        "count": 5,
        "timestamp": "15:23:40"
    },
    {
        "id": "P001061",
        "source": [
            "Park Street",
            "Sealdah",
            "Phoolbagan"
        ],
        "destination": "Ultadanga",
        "count": 6,
        "timestamp": "15:24:50"
    },
    {
        "id": "P001062",
        "source": [
            "Kasba",
            "Bosepukur",
            "Gariahat"
        ],
        "destination": "Esplanade",
        "count": 5,
        "timestamp": "15:20:31"
    },
    {
        "id": "P001063",
        "source": [
            "Karunamoyee",
            "Ultadanga",
            "Esplanade"
        ],
        "destination": "Howrah Station",
        "count": 6,
        "timestamp": "15:24:13"
    },
    {
        "id": "P001064",
        "source": [
            "Shyambazar",
            "Esplanade",
            "Park Circus"
        ],
        "destination": "Ruby Hospital",
        "count": 1,
        "timestamp": "15:22:23"
    }
]